[
    {
        "id": 1,
        "name": "MUSCULOSA",
        "description": "Musculosa blanca.",
        "category": "shirts",
        "colors": ["rojo", "azul", "blanco", "negro"],
        "sizes": ["s", "m", "l"],
        "price": 10000,
        "image": "img-musculosa.png"
    },
    {
        "id": 2,
        "name": "TOP CHALECO",
        "description": "Chaleco corte top.",
        "category": "shirts",
        "colors": ["rojo", "azul", "blanco"],
        "sizes": ["s", "m", "l", "xl"],
        "price": 25000,
        "image": "img-top-chaleco-1.png"
    },
    {
        "id": 3,
        "name": "VESTIDO CAMISERO",
        "description": "Camisa onda vestido, perfecto para el verano.",
        "category": "dresses",
        "colors": ["rojo", "azul", "blanco", "floreado"],
        "sizes": ["xs", "s", "m", "l"],
        "price": 30000,
        "image": "img-vestido-camisero.png"
    },
    {
        "id": 4,
        "name": "VESTIDO LARGO",
        "description": "Vestido largo.",
        "category": "dresses",
        "colors": ["rojo", "azul", "blanco", "negro"],
        "sizes": ["s", "l"],
        "price": 35000,
        "image": "img-vestido-largo.png"
    }
]